SackosArt/__init__.py
SackosArt/core/CoordCartesian.py
SackosArt/core/CoordCylindrical.py
SackosArt/core/CoordPolar.py
SackosArt/core/CoordSpherical.py
SackosArt/core/CoordSys.py
SackosArt/core/ImgFilter.py
SackosArt/core/__init__.py
SackosArt/docs/__init__.py
SackosArt/examples/__init__.py
SackosArt/examples/manipulate_image.py
SackosArt/examples/merge_two_images.py
SackosArt/examples/data/__init__.py
SackosArt/examples/data/img1.png
SackosArt/examples/data/img1_img2.jpg
SackosArt/examples/data/img2.png
SackosArt/tests/__init__.py
SackosArt/types/MathEquation.py
SackosArt/types/MathVar.py
SackosArt/types/SackosScriptResult.py
SackosArt/types/__init__.py
SackosArt/utils/__init__.py
sackosart-0.0.20.dist-info/licenses/LICENSE
sackosart-0.0.20.dist-info/METADATA
sackosart-0.0.20.dist-info/WHEEL
sackosart-0.0.20.dist-info/top_level.txt
sackosart-0.0.20.dist-info/RECORD
