Metadata-Version: 2.4
Name: SackosArt
Version: 0.0.20
Summary: SackosArt Software
Author-email: Josh <joshua.sackos@gmail.com>
License: MIT
Project-URL: Homepage, https://github.com/mrsackos/SackosArt
Project-URL: Bug Tracker, https://github.com/mrsackos/SackosArt/issues
Classifier: Programming Language :: Python :: 3
Classifier: License :: OSI Approved :: MIT License
Classifier: Operating System :: OS Independent
Classifier: Intended Audience :: Other Audience
Requires-Python: >=3.12
License-File: LICENSE
Dynamic: license-file
